README.md
setup.cfg
setup.py
stat_distr/Binomialdistribution.py
stat_distr/Gaussiandistribution.py
stat_distr/Generaldistribution.py
stat_distr/__init__.py
stat_distr.egg-info/PKG-INFO
stat_distr.egg-info/SOURCES.txt
stat_distr.egg-info/dependency_links.txt
stat_distr.egg-info/not-zip-safe
stat_distr.egg-info/top_level.txt