Metadata-Version: 1.0
Name: stat-distr
Version: 0.1
Summary: Statistic Distributions
Home-page: UNKNOWN
Author: Anna Xenaki
Author-email: UNKNOWN
License: UNKNOWN
Platform: UNKNOWN
